wasmer_py310-1.0.0.dist-info/METADATA
wasmer_py310-1.0.0.dist-info/WHEEL
wasmer/__init__.py
wasmer/wasmer.cpython-310-darwin.so
wasmer_py310-1.0.0.dist-info/RECORD
