Metadata-Version: 2.1
Name: wasmer-py310
Version: 1.0.0
Classifier: Programming Language :: Python
Classifier: Programming Language :: Python :: 3
Classifier: Programming Language :: Python :: 3.10
Classifier: Programming Language :: Python :: Implementation :: CPython
Classifier: Programming Language :: Rust
Classifier: Topic :: Software Development
Classifier: Topic :: Software Development :: Compilers
Classifier: Topic :: Software Development :: Interpreters
Classifier: License :: OSI Approved :: MIT License
Classifier: Operating System :: OS Independent
Summary: Python extension to run WebAssembly binaries
Keywords: python,extension,webassembly
Author: Wasmer Engineering Team <engineering@wasmer.io>
Author-email: Wasmer Engineering Team <engineering@wasmer.io>
Project-URL: Source Code, https://github.com/wasmerio/wasmer-python
Project-URL: Documentation, https://github.com/wasmerio/wasmer-python/
Project-URL: Bug Tracker, https://github.com/wasmerio/wasmer-python/issues
